Workbook

Sheet Painel
A1: CONTROLE DE ESTOQUE & VALIDADE
A2: Planilha editável para controle de produtos, movimentações, lotes e vencimentos.
A4: PRODUTOS CADASTRADOS | C4: ESTOQUE TOTAL (UN.) | E4: ESTOQUE BAIXO | G4: LOTES VENCIDOS
A5: =COUNTA(Produtos!A5:A204) | C5: =SUM(Produtos!H5:H204) | E5: =COUNTIF(Produtos!L5:L204,"BAIXO") | G5: =COUNTIF(Lotes!J5:J204,"VENCIDO")
A8: COMO USAR
A9: 1. Produtos: cadastre SKU, descrição, categoria, unidade, estoque inicial, mínimo, custo e preço de venda.
A10: 2. Movimentações: registre cada entrada e saída usando o mesmo SKU da aba Produtos.
A11: 3. Lotes: registre cada lote separadamente, com validade e quantidade disponível.
A12: 4. Alertas de validade são calculados automaticamente: vencido, até 7 dias e até 30 dias.
A13: 5. Revise as fórmulas e teste com dados fictícios antes de comercializar a planilha.

Sheet Produtos
A1: CADASTRO DE PRODUTOS
A2: Preencha os campos de cadastro; estoque atual, valor, margem e situação são calculados.
A4: SKU/Código | B4: Produto | C4: Categoria | D4: Unidade | E4: Estoque inicial | F4: Estoque mínimo | G4: Custo unitário (R$) | H4: Estoque atual | I4: Valor em estoque (R$) | J4: Preço de venda (R$) | K4: Margem bruta (%) | L4: Status estoque | M4: Fornecedor
H5: =IF(A5="","",E5+SUMIF(Movimentações!$C$5:$C$504,A5,Movimentações!$E$5:$E$504)-SUMIF(Movimentações!$C$5:$C$504,A5,Movimentações!$F$5:$F$504)) | I5: =IF(A5="","",H5*G5) | K5: =IFERROR((J5-G5)/J5,0) | L5: =IF(A5="","",IF(H5<=F5,"BAIXO","OK"))
H6: =IF(A6="","",E6+SUMIF(Movimentações!$C$5:$C$504,A6,Movimentações!$E$5:$E$504)-SUMIF(Movimentações!$C$5:$C$504,A6,Movimentações!$F$5:$F$504)) | I6: =IF(A6="","",H6*G6) | K6: =IFERROR((J6-G6)/J6,0) | L6: =IF(A6="","",IF(H6<=F6,"BAIXO","OK"))
H7: =IF(A7="","",E7+SUMIF(Movimentações!$C$5:$C$504,A7,Movimentações!$E$5:$E$504)-SUMIF(Movimentações!$C$5:$C$504,A7,Movimentações!$F$5:$F$504)) | I7: =IF(A7="","",H7*G7) | K7: =IFERROR((J7-G7)/J7,0) | L7: =IF(A7="","",IF(H7<=F7,"BAIXO","OK"))
H8: =IF(A8="","",E8+SUMIF(Movimentações!$C$5:$C$504,A8,Movimentações!$E$5:$E$504)-SUMIF(Movimentações!$C$5:$C$504,A8,Movimentações!$F$5:$F$504)) | I8: =IF(A8="","",H8*G8) | K8: =IFERROR((J8-G8)/J8,0) | L8: =IF(A8="","",IF(H8<=F8,"BAIXO","OK"))
H9: =IF(A9="","",E9+SUMIF(Movimentações!$C$5:$C$504,A9,Movimentações!$E$5:$E$504)-SUMIF(Movimentações!$C$5:$C$504,A9,Movimentações!$F$5:$F$504)) | I9: =IF(A9="","",H9*G9) | K9: =IFERROR((J9-G9)/J9,0) | L9: =IF(A9="","",IF(H9<=F9,"BAIXO","OK"))
H10: =IF(A10="","",E10+SUMIF(Movimentações!$C$5:$C$504,A10,Movimentações!$E$5:$E$504)-SUMIF(Movimentações!$C$5:$C$504,A10,Movimentações!$F$5:$F$504)) | I10: =IF(A10="","",H10*G10) | K10: =IFERROR((J10-G10)/J10,0) | L10: =IF(A10="","",IF(H10<=F10,"BAIXO","OK"))
H11: =IF(A11="","",E11+SUMIF(Movimentações!$C$5:$C$504,A11,Movimentações!$E$5:$E$504)-SUMIF(Movimentações!$C$5:$C$504,A11,Movimentações!$F$5:$F$504)) | I11: =IF(A11="","",H11*G11) | K11: =IFERROR((J11-G11)/J11,0) | L11: =IF(A11="","",IF(H11<=F11,"BAIXO","OK"))
H12: =IF(A12="","",E12+SUMIF(Movimentações!$C$5:$C$504,A12,Movimentações!$E$5:$E$504)-SUMIF(Movimentações!$C$5:$C$504,A12,Movimentações!$F$5:$F$504)) | I12: =IF(A12="","",H12*G12) | K12: =IFERROR((J12-G12)/J12,0) | L12: =IF(A12="","",IF(H12<=F12,"BAIXO","OK"))
H13: =IF(A13="","",E13+SUMIF(Movimentações!$C$5:$C$504,A13,Movimentações!$E$5:$E$504)-SUMIF(Movimentações!$C$5:$C$504,A13,Movimentações!$F$5:$F$504)) | I13: =IF(A13="","",H13*G13) | K13: =IFERROR((J13-G13)/J13,0) | L13: =IF(A13="","",IF(H13<=F13,"BAIXO","OK"))
H14: =IF(A14="","",E14+SUMIF(Movimentações!$C$5:$C$504,A14,Movimentações!$E$5:$E$504)-SUMIF(Movimentações!$C$5:$C$504,A14,Movimentações!$F$5:$F$504)) | I14: =IF(A14="","",H14*G14) | K14: =IFERROR((J14-G14)/J14,0) | L14: =IF(A14="","",IF(H14<=F14,"BAIXO","OK"))
H15: =IF(A15="","",E15+SUMIF(Movimentações!$C$5:$C$504,A15,Movimentações!$E$5:$E$504)-SUMIF(Movimentações!$C$5:$C$504,A15,Movimentações!$F$5:$F$504)) | I15: =IF(A15="","",H15*G15) | K15: =IFERROR((J15-G15)/J15,0) | L15: =IF(A15="","",IF(H15<=F15,"BAIXO","OK"))
H16: =IF(A16="","",E16+SUMIF(Movimentações!$C$5:$C$504,A16,Movimentações!$E$5:$E$504)-SUMIF(Movimentações!$C$5:$C$504,A16,Movimentações!$F$5:$F$504)) | I16: =IF(A16="","",H16*G16) | K16: =IFERROR((J16-G16)/J16,0) | L16: =IF(A16="","",IF(H16<=F16,"BAIXO","OK"))
... H204: =IF(A204="","",E204+SUMIF(Movimentações!$C$5:$C$504,A204,Movimentações!$E$5:$E$504)-SUMIF(Movimentações!$C$5:$C$504,A204,Movimentações!$F$5:$F$504)) | I204: =IF(A204="","",H204*G204) | K204: =IFERROR((J204-G204)/J204,0) | L204: =IF(A204="","",IF(H204<=F204,"BAIXO","OK"))

Sheet Movimentações
A1: ENTRADAS E SAÍDAS
A2: Use quantidades positivas nas colunas Entrada ou Saída; não preencha ambas na mesma linha.
A4: Data | B4: Tipo | C4: SKU/Código | D4: Produto/Descrição | E4: Entrada (qtde.) | F4: Saída (qtde.) | G4: Documento/Observação | H4: Responsável

Sheet Lotes
A1: CONTROLE DE LOTES E VENCIMENTOS
A2: Uma linha por lote. Informe validade e quantidade disponível para acompanhar os alertas.
A4: SKU/Código | B4: Produto | C4: Lote | D4: Data fabricação | E4: Data validade | F4: Qtd. recebida | G4: Qtd. disponível | H4: Dias até vencer | I4: Alerta | J4: Status | K4: Fornecedor
B5: =IFERROR(VLOOKUP(A5,Produtos!$A$5:$M$204,2,FALSE),"") | H5: =IF(E5="","",E5-TODAY()) | I5: =IF(E5="","",IF(E5<TODAY(),"VENCIDO",IF(E5<=TODAY()+7,"VENCE EM 7 DIAS",IF(E5<=TODAY()+30,"VENCE EM 30 DIAS","OK")))) | J5: =IF(A5="","",IF(G5<=0,"SEM ESTOQUE",IF(E5<TODAY(),"VENCIDO",IF(E5<=TODAY()+30,"ATENÇÃO","OK"))))
B6: =IFERROR(VLOOKUP(A6,Produtos!$A$5:$M$204,2,FALSE),"") | H6: =IF(E6="","",E6-TODAY()) | I6: =IF(E6="","",IF(E6<TODAY(),"VENCIDO",IF(E6<=TODAY()+7,"VENCE EM 7 DIAS",IF(E6<=TODAY()+30,"VENCE EM 30 DIAS","OK")))) | J6: =IF(A6="","",IF(G6<=0,"SEM ESTOQUE",IF(E6<TODAY(),"VENCIDO",IF(E6<=TODAY()+30,"ATENÇÃO","OK"))))
B7: =IFERROR(VLOOKUP(A7,Produtos!$A$5:$M$204,2,FALSE),"") | H7: =IF(E7="","",E7-TODAY()) | I7: =IF(E7="","",IF(E7<TODAY(),"VENCIDO",IF(E7<=TODAY()+7,"VENCE EM 7 DIAS",IF(E7<=TODAY()+30,"VENCE EM 30 DIAS","OK")))) | J7: =IF(A7="","",IF(G7<=0,"SEM ESTOQUE",IF(E7<TODAY(),"VENCIDO",IF(E7<=TODAY()+30,"ATENÇÃO","OK"))))
B8: =IFERROR(VLOOKUP(A8,Produtos!$A$5:$M$204,2,FALSE),"") | H8: =IF(E8="","",E8-TODAY()) | I8: =IF(E8="","",IF(E8<TODAY(),"VENCIDO",IF(E8<=TODAY()+7,"VENCE EM 7 DIAS",IF(E8<=TODAY()+30,"VENCE EM 30 DIAS","OK")))) | J8: =IF(A8="","",IF(G8<=0,"SEM ESTOQUE",IF(E8<TODAY(),"VENCIDO",IF(E8<=TODAY()+30,"ATENÇÃO","OK"))))
B9: =IFERROR(VLOOKUP(A9,Produtos!$A$5:$M$204,2,FALSE),"") | H9: =IF(E9="","",E9-TODAY()) | I9: =IF(E9="","",IF(E9<TODAY(),"VENCIDO",IF(E9<=TODAY()+7,"VENCE EM 7 DIAS",IF(E9<=TODAY()+30,"VENCE EM 30 DIAS","OK")))) | J9: =IF(A9="","",IF(G9<=0,"SEM ESTOQUE",IF(E9<TODAY(),"VENCIDO",IF(E9<=TODAY()+30,"ATENÇÃO","OK"))))
B10: =IFERROR(VLOOKUP(A10,Produtos!$A$5:$M$204,2,FALSE),"") | H10: =IF(E10="","",E10-TODAY()) | I10: =IF(E10="","",IF(E10<TODAY(),"VENCIDO",IF(E10<=TODAY()+7,"VENCE EM 7 DIAS",IF(E10<=TODAY()+30,"VENCE EM 30 DIAS","OK")))) | J10: =IF(A10="","",IF(G10<=0,"SEM ESTOQUE",IF(E10<TODAY(),"VENCIDO",IF(E10<=TODAY()+30,"ATENÇÃO","OK"))))
B11: =IFERROR(VLOOKUP(A11,Produtos!$A$5:$M$204,2,FALSE),"") | H11: =IF(E11="","",E11-TODAY()) | I11: =IF(E11="","",IF(E11<TODAY(),"VENCIDO",IF(E11<=TODAY()+7,"VENCE EM 7 DIAS",IF(E11<=TODAY()+30,"VENCE EM 30 DIAS","OK")))) | J11: =IF(A11="","",IF(G11<=0,"SEM ESTOQUE",IF(E11<TODAY(),"VENCIDO",IF(E11<=TODAY()+30,"ATENÇÃO","OK"))))
B12: =IFERROR(VLOOKUP(A12,Produtos!$A$5:$M$204,2,FALSE),"") | H12: =IF(E12="","",E12-TODAY()) | I12: =IF(E12="","",IF(E12<TODAY(),"VENCIDO",IF(E12<=TODAY()+7,"VENCE EM 7 DIAS",IF(E12<=TODAY()+30,"VENCE EM 30 DIAS","OK")))) | J12: =IF(A12="","",IF(G12<=0,"SEM ESTOQUE",IF(E12<TODAY(),"VENCIDO",IF(E12<=TODAY()+30,"ATENÇÃO","OK"))))
B13: =IFERROR(VLOOKUP(A13,Produtos!$A$5:$M$204,2,FALSE),"") | H13: =IF(E13="","",E13-TODAY()) | I13: =IF(E13="","",IF(E13<TODAY(),"VENCIDO",IF(E13<=TODAY()+7,"VENCE EM 7 DIAS",IF(E13<=TODAY()+30,"VENCE EM 30 DIAS","OK")))) | J13: =IF(A13="","",IF(G13<=0,"SEM ESTOQUE",IF(E13<TODAY(),"VENCIDO",IF(E13<=TODAY()+30,"ATENÇÃO","OK"))))
B14: =IFERROR(VLOOKUP(A14,Produtos!$A$5:$M$204,2,FALSE),"") | H14: =IF(E14="","",E14-TODAY()) | I14: =IF(E14="","",IF(E14<TODAY(),"VENCIDO",IF(E14<=TODAY()+7,"VENCE EM 7 DIAS",IF(E14<=TODAY()+30,"VENCE EM 30 DIAS","OK")))) | J14: =IF(A14="","",IF(G14<=0,"SEM ESTOQUE",IF(E14<TODAY(),"VENCIDO",IF(E14<=TODAY()+30,"ATENÇÃO","OK"))))
B15: =IFERROR(VLOOKUP(A15,Produtos!$A$5:$M$204,2,FALSE),"") | H15: =IF(E15="","",E15-TODAY()) | I15: =IF(E15="","",IF(E15<TODAY(),"VENCIDO",IF(E15<=TODAY()+7,"VENCE EM 7 DIAS",IF(E15<=TODAY()+30,"VENCE EM 30 DIAS","OK")))) | J15: =IF(A15="","",IF(G15<=0,"SEM ESTOQUE",IF(E15<TODAY(),"VENCIDO",IF(E15<=TODAY()+30,"ATENÇÃO","OK"))))
B16: =IFERROR(VLOOKUP(A16,Produtos!$A$5:$M$204,2,FALSE),"") | H16: =IF(E16="","",E16-TODAY()) | I16: =IF(E16="","",IF(E16<TODAY(),"VENCIDO",IF(E16<=TODAY()+7,"VENCE EM 7 DIAS",IF(E16<=TODAY()+30,"VENCE EM 30 DIAS","OK")))) | J16: =IF(A16="","",IF(G16<=0,"SEM ESTOQUE",IF(E16<TODAY(),"VENCIDO",IF(E16<=TODAY()+30,"ATENÇÃO","OK"))))
... B204: =IFERROR(VLOOKUP(A204,Produtos!$A$5:$M$204,2,FALSE),"") | H204: =IF(E204="","",E204-TODAY()) | I204: =IF(E204="","",IF(E204<TODAY(),"VENCIDO",IF(E204<=TODAY()+7,"VENCE EM 7 DIAS",IF(E204<=TODAY()+30,"VENCE EM 30 DIAS","OK")))) | J204: =IF(A204="","",IF(G204<=0,"SEM ESTOQUE",IF(E204<TODAY(),"VENCIDO",IF(E204<=TODAY()+30,"ATENÇÃO","OK"))))

Sheet Resumo Mensal
A1: RESUMO MENSAL
A3: Mês de referência | B3: 46296
A5: Indicador | B5: Resultado
A6: Entradas no mês | B6: =SUMIFS(Movimentações!E5:E504,Movimentações!A5:A504,">="&B3,Movimentações!A5:A504,"<"&EDATE(B3,1))
A7: Saídas no mês | B7: =SUMIFS(Movimentações!F5:F504,Movimentações!A5:A504,">="&B3,Movimentações!A5:A504,"<"&EDATE(B3,1))
A8: Produtos com estoque baixo | B8: =COUNTIF(Produtos!L5:L204,"BAIXO")
A9: Lotes vencidos | B9: =COUNTIF(Lotes!I5:I204,"VENCIDO")
A10: Lotes vencendo em até 7 dias | B10: =COUNTIF(Lotes!I5:I204,"VENCE EM 7 DIAS")
A11: Lotes vencendo em até 30 dias | B11: =COUNTIF(Lotes!I5:I204,"VENCE EM 30 DIAS")
